thesr/__init__.py
thesr/thesr.py
thesr-0.0.15.dist-info/licenses/LICENSE.txt
thesr-0.0.15.dist-info/METADATA
thesr-0.0.15.dist-info/WHEEL
thesr-0.0.15.dist-info/top_level.txt
thesr-0.0.15.dist-info/RECORD
