Metadata-Version: 2.4
Name: thesr
Version: 0.0.15
Summary: thesaurus (and also dictionary)
Home-page: https://github.com/treatmesubj/Thesaurus_Rex
Download-URL: https://github.com/treatmesubj/Thesaurus_Rex/archive/refs/tags/v0.0.15.tar.gz
Author: John Hupperts
Author-email: jrock4503@hotmail.com
License: gpl-3.0
Project-URL: Source, https://github.com/treatmesubj/Thesaurus_Rex
License-File: LICENSE.txt
Requires-Dist: requests
Requires-Dist: beautifulsoup4
Requires-Dist: rich
Dynamic: author
Dynamic: author-email
Dynamic: description
Dynamic: description-content-type
Dynamic: download-url
Dynamic: home-page
Dynamic: license
Dynamic: license-file
Dynamic: project-url
Dynamic: requires-dist
Dynamic: summary
